range_compression/__init__.py
range_compression/range_compression.py
range_compression-0.5.0.dist-info/METADATA
range_compression-0.5.0.dist-info/WHEEL
range_compression-0.5.0.dist-info/RECORD
