Metadata-Version: 2.1
Name: range-compression
Version: 0.5.0
Summary: 
Home-page: https://github.com/myuanz/matrix-range-compression
License: LGPL
Author: myuan
Author-email: zhengmy@ion.ac.cn
Requires-Python: >=3.9,<3.13
Classifier: License :: Other/Proprietary License
Classifier: Programming Language :: Python :: 3
Classifier: Programming Language :: Python :: 3.9
Classifier: Programming Language :: Python :: 3.10
Classifier: Programming Language :: Python :: 3.11
Classifier: Programming Language :: Python :: 3.12
Requires-Dist: importlib-metadata (>=6.6.0,<7.0.0) ; python_version >= "3.8" and python_version < "4.0"
Requires-Dist: numba (>=0.59)
Requires-Dist: numpy (>=1.26,<2)
Requires-Dist: polars (>=0.18)
Project-URL: Repository, https://github.com/myuanz/matrix-range-compression
